ptyx_mcq/TODO.odt
ptyx_mcq/__init__.py
ptyx_mcq/cli.py
ptyx_mcq/data/templates/original/README.txt
ptyx_mcq/data/templates/original/new.ptyx
ptyx_mcq/data/templates/original/questions/question1.ex
ptyx_mcq/data/templates/original/questions/question2.ex
ptyx_mcq/data/templates/original/questions/question3.ex
ptyx_mcq/data/templates/original/questions/question4.ex
ptyx_mcq/data/templates/original/scan/README.txt
ptyx_mcq/dev_cli.py
ptyx_mcq/make/__init__.py
ptyx_mcq/make/exercises_parsing.py
ptyx_mcq/make/extend_latex_generator.py
ptyx_mcq/make/generate_ptyx_code.py
ptyx_mcq/make/header.py
ptyx_mcq/make/include_directives_parsing.py
ptyx_mcq/make/make.py
ptyx_mcq/make/parser_tools.py
ptyx_mcq/parameters.py
ptyx_mcq/py.typed
ptyx_mcq/scan/__init__.py
ptyx_mcq/scan/data_gestion/__init__.py
ptyx_mcq/scan/data_gestion/conflict_handling/__init__.py
ptyx_mcq/scan/data_gestion/conflict_handling/config.py
ptyx_mcq/scan/data_gestion/conflict_handling/data_check/__init__.py
ptyx_mcq/scan/data_gestion/conflict_handling/data_check/check.py
ptyx_mcq/scan/data_gestion/conflict_handling/data_check/cl_fix.py
ptyx_mcq/scan/data_gestion/conflict_handling/data_check/fix.py
ptyx_mcq/scan/data_gestion/conflict_handling/integrity_check/__init__.py
ptyx_mcq/scan/data_gestion/conflict_handling/integrity_check/check.py
ptyx_mcq/scan/data_gestion/conflict_handling/integrity_check/cl_fix.py
ptyx_mcq/scan/data_gestion/conflict_handling/integrity_check/fix.py
ptyx_mcq/scan/data_gestion/data_handler.py
ptyx_mcq/scan/data_gestion/document_data.py
ptyx_mcq/scan/data_gestion/paths_handler.py
ptyx_mcq/scan/pdf/__init__.py
ptyx_mcq/scan/pdf/amend.py
ptyx_mcq/scan/pdf/pdftools.py
ptyx_mcq/scan/picture_analyze/__init__.py
ptyx_mcq/scan/picture_analyze/calibration.py
ptyx_mcq/scan/picture_analyze/checkbox_analyzer.py
ptyx_mcq/scan/picture_analyze/image_viewer.py
ptyx_mcq/scan/picture_analyze/scan_pic.py
ptyx_mcq/scan/picture_analyze/square_detection.py
ptyx_mcq/scan/picture_analyze/types_declaration.py
ptyx_mcq-28.0.0.dist-info/METADATA
ptyx_mcq-28.0.0.dist-info/WHEEL
ptyx_mcq-28.0.0.dist-info/entry_points.txt
ptyx_mcq-28.0.0.dist-info/RECORD
