Metadata-Version: 2.1
Name: ptyx-mcq
Version: 28.0.0
Summary: pTyX-MCQ is a generator/scanner of MCQ, based on pTyX.
Home-page: https://github.com/wxgeo/ptyx
License: GPL-3.0-or-later
Keywords: python,tikz,latex,pdf,exam,mcq,student
Author: Nicolas Pourcelot
Author-email: nicolas.pourcelot@gmail.com
Requires-Python: >=3.10,<4.0
Classifier: License :: OSI Approved :: GNU General Public License v3 or later (GPLv3+)
Classifier: Programming Language :: Python :: 3
Classifier: Programming Language :: Python :: 3.10
Classifier: Programming Language :: Python :: 3.11
Classifier: Programming Language :: Python :: 3.12
Requires-Dist: Pillow (>=9.2,<10.0)
Requires-Dist: argcomplete (>=3.1.2,<4.0.0)
Requires-Dist: numpy (>=1.23.0,<2.0.0)
Requires-Dist: openpyxl (>=3.1.2,<4.0.0)
Requires-Dist: platformdirs (>=4,<5)
Requires-Dist: ptyx (>=28.2,<29.0)
Requires-Dist: pymupdf (>=1.21.1,<2.0.0)
Requires-Dist: smallgraphlib (>=0.10)
Requires-Dist: sympy (>=1.11,<1.12)
Project-URL: Repository, https://github.com/wxgeo/ptyx
